hatesonar/__init__.py
hatesonar/api.py
hatesonar/crawler/__init__.py
hatesonar/crawler/blog.py
hatesonar/crawler/twitter.py
hatesonar/data/model.joblib
hatesonar/data/preprocess.joblib
hatesonar/trainer/__init__.py
hatesonar/trainer/model.py
hatesonar/trainer/preprocess.py
hatesonar/trainer/task.py
hatesonar-0.0.7.dist-info/LICENSE
hatesonar-0.0.7.dist-info/METADATA
hatesonar-0.0.7.dist-info/WHEEL
hatesonar-0.0.7.dist-info/top_level.txt
hatesonar-0.0.7.dist-info/RECORD
