Metadata-Version: 2.1
Name: hatesonar
Version: 0.0.7
Summary: Hate Speech Detection Library for Python
Home-page: https://github.com/Hironsan/HateSonar
Author: Hironsan
Author-email: hiroki.nakayama.py@gmail.com
License: MIT
Platform: UNKNOWN
Classifier: License :: OSI Approved :: MIT License
Classifier: Programming Language :: Python
Classifier: Programming Language :: Python :: 2.7
Classifier: Programming Language :: Python :: 3.4
Classifier: Programming Language :: Python :: 3.5
Classifier: Programming Language :: Python :: 3.6
Classifier: Programming Language :: Python :: Implementation :: CPython
Classifier: Programming Language :: Python :: Implementation :: PyPy
Requires-Dist: numpy (>=1.14.0)
Requires-Dist: pandas (>=0.22.0)
Requires-Dist: scikit-learn (>=0.19.1)
Requires-Dist: scipy (>=1.0.0)
Requires-Dist: joblib (>=0.16.0)
